[
  {
    "id": "979543ff-20f1-456b-8fab-000da86c0fb0",
    "name": "Telit Test",
    "subdomain": "telit",
    "repoUrl": "daniwally/telit",
    "status": "active",
    "createdAt": "2026-04-01T12:25:09.380Z",
    "updatedAt": "2026-04-01T12:25:09.380Z"
  },
  {
    "name": "lost",
    "description": "proyecto lost muebles",
    "subdomain": "atelier",
    "repoUrl": "daniwally/lost",
    "status": "active",
    "id": "f53a8caf-f8b0-4659-a8f6-5cb3adb55357",
    "createdAt": "2026-04-01T12:53:09.173Z",
    "updatedAt": "2026-04-01T13:21:05.439Z"
  },
  {
    "name": "meals",
    "description": "presupuesto",
    "subdomain": "meals",
    "repoUrl": "daniwally/meals",
    "status": "active",
    "id": "906a8b1c-33b3-4782-84af-a430ee3d62d4",
    "createdAt": "2026-04-01T13:33:12.861Z",
    "updatedAt": "2026-04-01T13:33:12.861Z"
  },
  {
    "name": "meals",
    "description": "presupuesto",
    "subdomain": "meals",
    "repoUrl": "daniwally/meals",
    "status": "active",
    "id": "abe29201-2b82-4df2-b77a-52f4872646cd",
    "createdAt": "2026-04-01T13:33:17.178Z",
    "updatedAt": "2026-04-01T13:33:17.178Z"
  }
]